__init__.py
main.py
diagrams_manager-0.1.0.dist-info/METADATA
diagrams_manager-0.1.0.dist-info/WHEEL
diagrams_manager-0.1.0.dist-info/top_level.txt
diagrams_manager-0.1.0.dist-info/RECORD
