Metadata-Version: 2.4
Name: diagrams-manager
Version: 0.1.0
Summary: Add your description here
Requires-Python: >=3.12
Requires-Dist: dotenv>=0.9.9
Requires-Dist: gradio>=5.23.1
Requires-Dist: langchain>=1.0.3
Requires-Dist: langgraph>=1.0.2
Requires-Dist: pydantic>=2.12.3
